Metadata-Version: 2.1
Name: pymelsec
Version: 0.2.5
Summary: A Python MELSEC Communication library for communicating with Mitsubishi PLCs.
Home-page: https://github.com/NothinRandom/pymelsec
Author: Tri Quach
Author-email: nothinrandom@gmail.com
License: MIT
Requires-Python: >=3.7.0
License-File: LICENSE
